{
    "author": "nhcwebmaster@noaa.gov (NHC Webmaster)",
    "author_detail": {
        "email": "nhcwebmaster@noaa.gov",
        "name": "NHC Webmaster"
    },
    "authors": [
        {
            "email": "nhcwebmaster@noaa.gov",
            "name": "NHC Webmaster"
        }
    ],
    "guidislink": false,
    "id": "summary-al022024-202406300855",
    "link": "https://www.nhc.noaa.gov/text/refresh/MIATCPAT2+shtml/300855.shtml",
    "links": [
        {
            "href": "https://www.nhc.noaa.gov/text/refresh/MIATCPAT2+shtml/300855.shtml",
            "rel": "alternate",
            "type": "text/html"
        }
    ],
    "nhc_atcf": "AL022024",
    "nhc_center": "10.7, -53.1",
    "nhc_cyclone": "",
    "nhc_datetime": "5:00 AM AST Sun Jun 30",
    "nhc_headline": "...BERYL CONTINUING TO RAPIDLY INTENSIFY... ...FORECAST TO BRING LIFE-THREATENING WINDS AND STORM SURGE TO THE  WINDWARD ISLANDS AS AN EXTREMELY DANGEROUS HURRICANE...",
    "nhc_movement": "W at 21 mph",
    "nhc_name": "Beryl",
    "nhc_pressure": "981 mb",
    "nhc_type": "Hurricane",
    "nhc_wallet": "AT2",
    "nhc_wind": "100 mph",
    "published": "Sun, 30 Jun 2024 08:55:51 GMT",
    "published_parsed": [
        2024,
        6,
        30,
        8,
        55,
        51,
        6,
        182,
        0
    ],
    "summary": "...BERYL CONTINUING TO RAPIDLY INTENSIFY... ...FORECAST TO BRING LIFE-THREATENING WINDS AND STORM SURGE TO THE  WINDWARD ISLANDS AS AN EXTREMELY DANGEROUS HURRICANE...\n As of 5:00 AM AST Sun Jun 30\n the center of Beryl was located near 10.7, -53.1\n with movement W at 21 mph.\n The minimum central pressure was 981 mb\n with maximum sustained winds of about 100 mph.",
    "summary_detail": {
        "base": "https://www.nhc.noaa.gov/gis-at.xml",
        "language": null,
        "type": "text/html",
        "value": "...BERYL CONTINUING TO RAPIDLY INTENSIFY... ...FORECAST TO BRING LIFE-THREATENING WINDS AND STORM SURGE TO THE  WINDWARD ISLANDS AS AN EXTREMELY DANGEROUS HURRICANE...\n As of 5:00 AM AST Sun Jun 30\n the center of Beryl was located near 10.7, -53.1\n with movement W at 21 mph.\n The minimum central pressure was 981 mb\n with maximum sustained winds of about 100 mph."
    },
    "title": "Summary - Hurricane Beryl (AT2/AL022024)",
    "title_detail": {
        "base": "https://www.nhc.noaa.gov/gis-at.xml",
        "language": null,
        "type": "text/plain",
        "value": "Summary - Hurricane Beryl (AT2/AL022024)"
    }
}