{
    "author": "nhcwebmaster@noaa.gov (NHC Webmaster)",
    "author_detail": {
        "email": "nhcwebmaster@noaa.gov",
        "name": "NHC Webmaster"
    },
    "authors": [
        {
            "email": "nhcwebmaster@noaa.gov",
            "name": "NHC Webmaster"
        }
    ],
    "guidislink": false,
    "id": "gis-bt-shp-cp012025-019-202507312034",
    "link": "https://www.nhc.noaa.gov/gis/best_track/cp012025_best_track.zip",
    "links": [
        {
            "href": "https://www.nhc.noaa.gov/gis/best_track/cp012025_best_track.zip",
            "rel": "alternate",
            "type": "text/html"
        }
    ],
    "published": "Thu, 31 Jul 2025 20:34:25 GMT",
    "published_parsed": [
        2025,
        7,
        31,
        20,
        34,
        25,
        3,
        212,
        0
    ],
    "summary": "Track, Points, and Wind Swath. Shapefile last updated Thu, 31 Jul 2025 20:34:25 GMT",
    "summary_detail": {
        "base": "https://www.nhc.noaa.gov/gis-cp.xml",
        "language": null,
        "type": "text/html",
        "value": "Track, Points, and Wind Swath. Shapefile last updated Thu, 31 Jul 2025 20:34:25 GMT"
    },
    "title": "Preliminary Best Track [shp] - Tropical Storm Iona (CP1/CP012025)",
    "title_detail": {
        "base": "https://www.nhc.noaa.gov/gis-cp.xml",
        "language": null,
        "type": "text/plain",
        "value": "Preliminary Best Track [shp] - Tropical Storm Iona (CP1/CP012025)"
    }
}