{
    "author": "nhcwebmaster@noaa.gov (NHC Webmaster)",
    "author_detail": {
        "email": "nhcwebmaster@noaa.gov",
        "name": "NHC Webmaster"
    },
    "authors": [
        {
            "email": "nhcwebmaster@noaa.gov",
            "name": "NHC Webmaster"
        }
    ],
    "guidislink": false,
    "id": "gis-forecast-shp-al022024-020-202407031449",
    "link": "https://www.nhc.noaa.gov/gis/forecast/archive/al022024_5day_020.zip",
    "links": [
        {
            "href": "https://www.nhc.noaa.gov/gis/forecast/archive/al022024_5day_020.zip",
            "rel": "alternate",
            "type": "text/html"
        }
    ],
    "published": "Wed, 03 Jul 2024 14:49:45 GMT",
    "published_parsed": [
        2024,
        7,
        3,
        14,
        49,
        45,
        2,
        185,
        0
    ],
    "summary": "Forecast Track, Cone of Uncertainty, Watches/Warnings. Shapefile last updated Wed, 03 Jul 2024 14:49:45 GMT",
    "summary_detail": {
        "base": "https://www.nhc.noaa.gov/gis-at.xml",
        "language": null,
        "type": "text/html",
        "value": "Forecast Track, Cone of Uncertainty, Watches/Warnings. Shapefile last updated Wed, 03 Jul 2024 14:49:45 GMT"
    },
    "title": "Advisory #020 Forecast [shp] - Hurricane Beryl (AT2/AL022024)",
    "title_detail": {
        "base": "https://www.nhc.noaa.gov/gis-at.xml",
        "language": null,
        "type": "text/plain",
        "value": "Advisory #020 Forecast [shp] - Hurricane Beryl (AT2/AL022024)"
    }
}