{
    "author": "nhcwebmaster@noaa.gov (NHC Webmaster)",
    "author_detail": {
        "email": "nhcwebmaster@noaa.gov",
        "name": "NHC Webmaster"
    },
    "authors": [
        {
            "email": "nhcwebmaster@noaa.gov",
            "name": "NHC Webmaster"
        }
    ],
    "guidislink": false,
    "id": "gis-bt-shp-ep122024-202410220838",
    "link": "https://www.nhc.noaa.gov/gis/best_track/ep122024_best_track.zip",
    "links": [
        {
            "href": "https://www.nhc.noaa.gov/gis/best_track/ep122024_best_track.zip",
            "rel": "alternate",
            "type": "text/html"
        }
    ],
    "published": "Tue, 22 Oct 2024 08:38:21 GMT",
    "published_parsed": [
        2024,
        10,
        22,
        8,
        38,
        21,
        1,
        296,
        0
    ],
    "summary": "Track, Points, and Wind Swath. Shapefile last updated Tue, 22 Oct 2024 08:38:21 GMT",
    "summary_detail": {
        "base": "https://www.nhc.noaa.gov/gis-ep.xml",
        "language": null,
        "type": "text/html",
        "value": "Track, Points, and Wind Swath. Shapefile last updated Tue, 22 Oct 2024 08:38:21 GMT"
    },
    "title": "Preliminary Best Track [shp] - Tropical Storm Kristy (EP2/EP122024)",
    "title_detail": {
        "base": "https://www.nhc.noaa.gov/gis-ep.xml",
        "language": null,
        "type": "text/plain",
        "value": "Preliminary Best Track [shp] - Tropical Storm Kristy (EP2/EP122024)"
    }
}