{
    "author": "nhcwebmaster@noaa.gov (NHC Webmaster)",
    "author_detail": {
        "email": "nhcwebmaster@noaa.gov",
        "name": "NHC Webmaster"
    },
    "authors": [
        {
            "email": "nhcwebmaster@noaa.gov",
            "name": "NHC Webmaster"
        }
    ],
    "guidislink": false,
    "id": "summary-ep112024-202410030845",
    "link": "https://www.nhc.noaa.gov/text/refresh/MIATCPEP1+shtml/030845.shtml",
    "links": [
        {
            "href": "https://www.nhc.noaa.gov/text/refresh/MIATCPEP1+shtml/030845.shtml",
            "rel": "alternate",
            "type": "text/html"
        }
    ],
    "nhc_atcf": "EP112024",
    "nhc_center": "14.5, -95.9",
    "nhc_cyclone": "",
    "nhc_datetime": "3:00 AM CST Thu Oct 3",
    "nhc_headline": "...CONTINUED HEAVY RAINS EXPECTED TO PRODUCE FLOODING AND MUDSLIDES IN PORTIONS OF SOUTHERN MEXICO... ...TROPICAL STORM WARNING REMAINS IN EFFECT...",
    "nhc_movement": "NE at 2 mph",
    "nhc_name": "Eleven-E",
    "nhc_pressure": "1004 mb",
    "nhc_type": "Tropical Depression",
    "nhc_wallet": "EP1",
    "nhc_wind": "35 mph",
    "published": "Thu, 03 Oct 2024 08:45:51 GMT",
    "published_parsed": [
        2024,
        10,
        3,
        8,
        45,
        51,
        3,
        277,
        0
    ],
    "summary": "...CONTINUED HEAVY RAINS EXPECTED TO PRODUCE FLOODING AND MUDSLIDES IN PORTIONS OF SOUTHERN MEXICO... ...TROPICAL STORM WARNING REMAINS IN EFFECT...\n As of 3:00 AM CST Thu Oct 3\n the center of Eleven-E was located near 14.5, -95.9\n with movement NE at 2 mph.\n The minimum central pressure was 1004 mb\n with maximum sustained winds of about 35 mph.",
    "summary_detail": {
        "base": "https://www.nhc.noaa.gov/gis-ep.xml",
        "language": null,
        "type": "text/html",
        "value": "...CONTINUED HEAVY RAINS EXPECTED TO PRODUCE FLOODING AND MUDSLIDES IN PORTIONS OF SOUTHERN MEXICO... ...TROPICAL STORM WARNING REMAINS IN EFFECT...\n As of 3:00 AM CST Thu Oct 3\n the center of Eleven-E was located near 14.5, -95.9\n with movement NE at 2 mph.\n The minimum central pressure was 1004 mb\n with maximum sustained winds of about 35 mph."
    },
    "title": "Summary - Tropical Depression Eleven-E (EP1/EP112024)",
    "title_detail": {
        "base": "https://www.nhc.noaa.gov/gis-ep.xml",
        "language": null,
        "type": "text/plain",
        "value": "Summary - Tropical Depression Eleven-E (EP1/EP112024)"
    }
}