{
    "author": "nhcwebmaster@noaa.gov (NHC Webmaster)",
    "author_detail": {
        "email": "nhcwebmaster@noaa.gov",
        "name": "NHC Webmaster"
    },
    "authors": [
        {
            "email": "nhcwebmaster@noaa.gov",
            "name": "NHC Webmaster"
        }
    ],
    "guidislink": false,
    "id": "summary-ep182025-202510290241",
    "link": "https://www.nhc.noaa.gov/text/MIATCPEP3.shtml",
    "links": [
        {
            "href": "https://www.nhc.noaa.gov/text/MIATCPEP3.shtml",
            "rel": "alternate",
            "type": "text/html"
        }
    ],
    "nhc_atcf": "EP182025",
    "nhc_center": "15.4, -125.3",
    "nhc_cyclone": "",
    "nhc_datetime": "8:00 PM PDT Tue Oct 28",
    "nhc_headline": "...SONIA REMAINS A TROPICAL STORM, EXPECTED TO WEAKEN INTO A REMNANT LOW LATER TONIGHT...",
    "nhc_movement": "W at 12 mph",
    "nhc_name": "Sonia",
    "nhc_pressure": "1005 mb",
    "nhc_type": "Tropical Storm",
    "nhc_wallet": "EP3",
    "nhc_wind": "40 mph",
    "published": "Wed, 29 Oct 2025 02:41:19 GMT",
    "published_parsed": [
        2025,
        10,
        29,
        2,
        41,
        19,
        2,
        302,
        0
    ],
    "summary": "...SONIA REMAINS A TROPICAL STORM, EXPECTED TO WEAKEN INTO A REMNANT LOW LATER TONIGHT... As of 8:00 PM PDT Tue Oct 28 the center of Sonia was located near 15.4, -125.3 with movement W at 12 mph. The minimum central pressure was 1005 mb with maximum sustained winds of about 40 mph.",
    "summary_detail": {
        "base": "https://www.nhc.noaa.gov/gis-ep.xml",
        "language": null,
        "type": "text/html",
        "value": "...SONIA REMAINS A TROPICAL STORM, EXPECTED TO WEAKEN INTO A REMNANT LOW LATER TONIGHT... As of 8:00 PM PDT Tue Oct 28 the center of Sonia was located near 15.4, -125.3 with movement W at 12 mph. The minimum central pressure was 1005 mb with maximum sustained winds of about 40 mph."
    },
    "title": "Summary - Tropical Storm Sonia (EP3/EP182025)",
    "title_detail": {
        "base": "https://www.nhc.noaa.gov/gis-ep.xml",
        "language": null,
        "type": "text/plain",
        "value": "Summary - Tropical Storm Sonia (EP3/EP182025)"
    }
}