<?xml version="1.0"?>
<cycloneMessage>
<!-- System Advisory Meta Information -->
<atcfID>CP012024</atcfID>
<issuingUnit>NWS CENTRAL PACIFIC HURRICANE CENTER HONOLULU HI</issuingUnit>
<messageType>ROUTINE ADVISORY</messageType>
<messageBinNumber>1</messageBinNumber>
<advisoryNumber>35</advisoryNumber>
<!-- System Date/Time Information -->
<messageDateTimeLocal>20240830 05:00:00 PM HST</messageDateTimeLocal>
<messageDateTimeUTC>20240831 03:00:00 AM UTC</messageDateTimeUTC>
<messageDateTimeUTC24>202408310300</messageDateTimeUTC24>
<messageDateTimeLocalStr>0500 PM HST Fri Aug 30</messageDateTimeLocalStr>
<timeEpochSeconds>1725073200</timeEpochSeconds>
<!-- System state defined -->
<systemType>TROPICAL DEPRESSION</systemType>
<systemName>HONE</systemName>
<!-- Center Location of the System -->
<!-- Lattitude: North is positive; South is negative -->
<!-- Longitude: East is positive; West is negative -->
<!-- units: decimal degrees (tenths) -->
<centerLocLatitude>22.0</centerLocLatitude>
<centerLocLongitude>-176</centerLocLongitude>
<!-- Lattitude: North is N; South is S -->
<!-- Longitude: East is E; West is W -->
<!-- units: decimal degrees (tenths) -->
<centerLocLatitudeExpanded>22.0N</centerLocLatitudeExpanded>
<centerLocLongitudeExpanded>176.0W</centerLocLongitudeExpanded>
<!-- Maximum Intensity of the System -->
<!-- units: MPH, KPH, KTS, MB and/or INCHES HG -->
<systemIntensityMph>35</systemIntensityMph>
<systemIntensityKph>55</systemIntensityKph>
<systemIntensityKts>30</systemIntensityKts>
<systemMslpMb>1009</systemMslpMb>
<systemMslpInHg>29.80</systemMslpInHg>
<systemSaffirSimpsonCategory>N/A</systemSaffirSimpsonCategory>
<formationChancePct48h>N/A</formationChancePct48h>
<formationChancePct7d>N/A</formationChancePct7d>
<!-- Current System Movement -->
<!-- units: Degrees, MPH and KPH -->
<systemDirectionOfMotion>WNW OR 290 DEGREES</systemDirectionOfMotion>
<systemSpeedMph>6</systemSpeedMph>
<systemSpeedKph>9</systemSpeedKph>
<systemSpeedKts>5</systemSpeedKts>
<!-- Current System Location from known Reference Point -->
<systemGeoRefPt1>ABOUT 435 MI...705 KM SSE OF MIDWAY ISLAND</systemGeoRefPt1>
<systemGeoRefPt2>ABOUT 1160 MI...1870 KM W OF HONOLULU HAWAII</systemGeoRefPt2>
<!-- Relevant Message -->
<message>
ZCZC HFOTCPCP1 ALL
TTAA00 PHFO DDHHMM
 
BULLETIN
Tropical Depression Hone Advisory Number  35
NWS Central Pacific Hurricane Center Honolulu HI   CP012024
500 PM HST Fri Aug 30 2024
 
...HONE SLOWS BUT IS EXPECTED TO TURN TO THE NORTHWEST AND
STRENGTHEN TONIGHT AND SATURDAY...
 
 
SUMMARY OF 500 PM HST...0300 UTC...INFORMATION
----------------------------------------------
LOCATION...22.0N 176.0W
ABOUT 435 MI...705 KM SSE OF MIDWAY ISLAND
ABOUT 1160 MI...1870 KM W OF HONOLULU HAWAII
MAXIMUM SUSTAINED WINDS...35 MPH...55 KM/H
PRESENT MOVEMENT...WNW OR 290 DEGREES AT 6 MPH...9 KM/H
MINIMUM CENTRAL PRESSURE...1009 MB...29.80 INCHES
 
 
WATCHES AND WARNINGS
--------------------
CHANGES WITH THIS ADVISORY:
 
None.
 
SUMMARY OF WATCHES AND WARNINGS IN EFFECT:
 
A Tropical Storm Watch is in effect for...
 
* Kure Atoll
* Midway Atoll
* Portions of the Papahanaumokuakea Marine National
Monument from Lisianski Island to Pearl and Hermes Atoll
 
A Tropical Storm Watch means tropical storm conditions are
possible in the watch area within 48 hours.
 
For storm information specific to your area, please monitor
products issued by the National Weather Service office in
Honolulu Hawaii.
 
 
DISCUSSION AND OUTLOOK
----------------------
At 500 PM HST (0300 UTC), the center of Tropical Depression Hone was
located near latitude 22.0 North, longitude 176.0 West. The
depression is moving toward the west-northwest near 6 mph (9 
km/h). A turn to the north-northwest is expected through tomorrow. 
Hone is then expected to move to the west-northwest at a 
slower forward speed through Sunday. On the forecast track, Hone is 
expected to pass south of Kure, Midway and Pearl and Hermes Atolls 
Saturday night into Sunday.
 
Maximum sustained winds are near 35 mph (55 km/h) with higher gusts.
Gradual strengthening is forecast over the next couple of days, 
with Hone expected to become a tropical storm Saturday.

The estimated minimum central pressure is 1009 mb (29.80 inches).
 
 
HAZARDS AFFECTING LAND
----------------------
WIND: Tropical storm conditions are possible within the watch area
late Saturday into Sunday.
 
RAINFALL: Storm total rainfall of 2 to 4 inches is possible over
Midway, Kure and Pearl and Hermes Atolls.
 
 
NEXT ADVISORY
-------------
Next intermediate advisory at 800 PM HST.
Next complete advisory at 1100 PM HST.
 
$$
Forecaster M Ballard
 
NNNN
 
</message>
</cycloneMessage>
