{
    "author": "nhcwebmaster@noaa.gov (NHC Webmaster)",
    "author_detail": {
        "email": "nhcwebmaster@noaa.gov",
        "name": "NHC Webmaster"
    },
    "authors": [
        {
            "email": "nhcwebmaster@noaa.gov",
            "name": "NHC Webmaster"
        }
    ],
    "guidislink": false,
    "id": "summary-ep052024-202408060244",
    "link": "https://www.nhc.noaa.gov/text/refresh/MIATCPEP5+shtml/060244.shtml",
    "links": [
        {
            "href": "https://www.nhc.noaa.gov/text/refresh/MIATCPEP5+shtml/060244.shtml",
            "rel": "alternate",
            "type": "text/html"
        }
    ],
    "nhc_atcf": "EP052024",
    "nhc_center": "13.8, -114.3",
    "nhc_cyclone": "",
    "nhc_datetime": "8:00 PM MST Mon Aug 5",
    "nhc_headline": "...EMILIA DRIFTING SOUTHWESTWARD WITH LITTLE CHANGE IN STRENGTH...",
    "nhc_movement": "WSW at 2 mph",
    "nhc_name": "Emilia",
    "nhc_pressure": "997 mb",
    "nhc_type": "Tropical Storm",
    "nhc_wallet": "EP5",
    "nhc_wind": "50 mph",
    "published": "Tue, 06 Aug 2024 02:44:34 GMT",
    "published_parsed": [
        2024,
        8,
        6,
        2,
        44,
        34,
        1,
        219,
        0
    ],
    "summary": "...EMILIA DRIFTING SOUTHWESTWARD WITH LITTLE CHANGE IN STRENGTH...\n As of 8:00 PM MST Mon Aug 5\n the center of Emilia was located near 13.8, -114.3\n with movement WSW at 2 mph.\n The minimum central pressure was 997 mb\n with maximum sustained winds of about 50 mph.",
    "summary_detail": {
        "base": "https://www.nhc.noaa.gov/gis-ep.xml",
        "language": null,
        "type": "text/html",
        "value": "...EMILIA DRIFTING SOUTHWESTWARD WITH LITTLE CHANGE IN STRENGTH...\n As of 8:00 PM MST Mon Aug 5\n the center of Emilia was located near 13.8, -114.3\n with movement WSW at 2 mph.\n The minimum central pressure was 997 mb\n with maximum sustained winds of about 50 mph."
    },
    "title": "Summary - Tropical Storm Emilia (EP5/EP052024)",
    "title_detail": {
        "base": "https://www.nhc.noaa.gov/gis-ep.xml",
        "language": null,
        "type": "text/plain",
        "value": "Summary - Tropical Storm Emilia (EP5/EP052024)"
    }
}