{
    "author": "nhcwebmaster@noaa.gov (NHC Webmaster)",
    "author_detail": {
        "email": "nhcwebmaster@noaa.gov",
        "name": "NHC Webmaster"
    },
    "authors": [
        {
            "email": "nhcwebmaster@noaa.gov",
            "name": "NHC Webmaster"
        }
    ],
    "guidislink": false,
    "id": "summary-ep052025-202506190852",
    "link": "https://www.nhc.noaa.gov/text/MIATCPEP5.shtml",
    "links": [
        {
            "href": "https://www.nhc.noaa.gov/text/MIATCPEP5.shtml",
            "rel": "alternate",
            "type": "text/html"
        }
    ],
    "nhc_atcf": "EP052025",
    "nhc_center": "15.9, -97.9",
    "nhc_cyclone": "",
    "nhc_datetime": "3:00 AM CST Thu Jun 19",
    "nhc_headline": "...ERICK VERY NEAR THE COAST OF MEXICO... ...BRINGING EXTREMELY DESTRUCTIVE WINDS NEAR ITS CORE...",
    "nhc_movement": "NW at 9 mph",
    "nhc_name": "Erick",
    "nhc_pressure": "940 mb",
    "nhc_type": "Hurricane",
    "nhc_wallet": "EP5",
    "nhc_wind": "140 mph",
    "published": "Thu, 19 Jun 2025 08:52:01 GMT",
    "published_parsed": [
        2025,
        6,
        19,
        8,
        52,
        1,
        3,
        170,
        0
    ],
    "summary": "...ERICK VERY NEAR THE COAST OF MEXICO... ...BRINGING EXTREMELY DESTRUCTIVE WINDS NEAR ITS CORE... As of 3:00 AM CST Thu Jun 19 the center of Erick was located near 15.9, -97.9 with movement NW at 9 mph. The minimum central pressure was 940 mb with maximum sustained winds of about 140 mph.",
    "summary_detail": {
        "base": "https://www.nhc.noaa.gov/gis-ep.xml",
        "language": null,
        "type": "text/html",
        "value": "...ERICK VERY NEAR THE COAST OF MEXICO... ...BRINGING EXTREMELY DESTRUCTIVE WINDS NEAR ITS CORE... As of 3:00 AM CST Thu Jun 19 the center of Erick was located near 15.9, -97.9 with movement NW at 9 mph. The minimum central pressure was 940 mb with maximum sustained winds of about 140 mph."
    },
    "title": "Summary for Hurricane Erick (EP5/EP052025)",
    "title_detail": {
        "base": "https://www.nhc.noaa.gov/gis-ep.xml",
        "language": null,
        "type": "text/plain",
        "value": "Summary for Hurricane Erick (EP5/EP052025)"
    }
}