{
    "author": "nhcwebmaster@noaa.gov (NHC Webmaster)",
    "author_detail": {
        "email": "nhcwebmaster@noaa.gov",
        "name": "NHC Webmaster"
    },
    "authors": [
        {
            "email": "nhcwebmaster@noaa.gov",
            "name": "NHC Webmaster"
        }
    ],
    "guidislink": false,
    "id": "summary-al102024-202409260839",
    "link": "https://www.nhc.noaa.gov/text/refresh/MIATCPAT5+shtml/260839.shtml",
    "links": [
        {
            "href": "https://www.nhc.noaa.gov/text/refresh/MIATCPAT5+shtml/260839.shtml",
            "rel": "alternate",
            "type": "text/html"
        }
    ],
    "nhc_atcf": "AL102024",
    "nhc_center": "37.1, -52.8",
    "nhc_cyclone": "",
    "nhc_datetime": "5:00 AM AST Thu Sep 26",
    "nhc_headline": "...ISAAC CONTINUES EASTWARD AND COULD BECOME A HURRICANE IN A COUPLE OF DAYS...",
    "nhc_movement": "E at 12 mph",
    "nhc_name": "Isaac",
    "nhc_pressure": "997 mb",
    "nhc_type": "TROPICAL STORM",
    "nhc_wallet": "AT5",
    "nhc_wind": "50 mph",
    "published": "Thu, 26 Sep 2024 08:39:23 GMT",
    "published_parsed": [
        2024,
        9,
        26,
        8,
        39,
        23,
        3,
        270,
        0
    ],
    "summary": "...ISAAC CONTINUES EASTWARD AND COULD BECOME A HURRICANE IN A COUPLE OF DAYS...\n As of 5:00 AM AST Thu Sep 26\n the center of Isaac was located near 37.1, -52.8\n with movement E at 12 mph.\n The minimum central pressure was 997 mb\n with maximum sustained winds of about 50 mph.",
    "summary_detail": {
        "base": "https://www.nhc.noaa.gov/gis-at.xml",
        "language": null,
        "type": "text/html",
        "value": "...ISAAC CONTINUES EASTWARD AND COULD BECOME A HURRICANE IN A COUPLE OF DAYS...\n As of 5:00 AM AST Thu Sep 26\n the center of Isaac was located near 37.1, -52.8\n with movement E at 12 mph.\n The minimum central pressure was 997 mb\n with maximum sustained winds of about 50 mph."
    },
    "title": "Summary - Tropical Storm Isaac (AT5/AL102024)",
    "title_detail": {
        "base": "https://www.nhc.noaa.gov/gis-at.xml",
        "language": null,
        "type": "text/plain",
        "value": "Summary - Tropical Storm Isaac (AT5/AL102024)"
    }
}