{
    "author": "nhcwebmaster@noaa.gov (NHC Webmaster)",
    "author_detail": {
        "email": "nhcwebmaster@noaa.gov",
        "name": "NHC Webmaster"
    },
    "authors": [
        {
            "email": "nhcwebmaster@noaa.gov",
            "name": "NHC Webmaster"
        }
    ],
    "guidislink": false,
    "id": "summary-al042025-202508061443",
    "link": "https://www.nhc.noaa.gov/text/MIATCPAT4.shtml",
    "links": [
        {
            "href": "https://www.nhc.noaa.gov/text/MIATCPAT4.shtml",
            "rel": "alternate",
            "type": "text/html"
        }
    ],
    "nhc_atcf": "AL042025",
    "nhc_center": "39.9, -58.2",
    "nhc_cyclone": "",
    "nhc_datetime": "11:00 AM AST Wed Aug 06",
    "nhc_headline": "...DEXTER STRENGTHENS A LITTLE MORE... ...LIKELY TO BECOME A POWERFUL EXTRATROPICAL CYCLONE BY FRIDAY AS IT TRAVERSES THE NORTH ATLANTIC...",
    "nhc_movement": "ENE at 15 mph",
    "nhc_name": "Dexter",
    "nhc_pressure": "999 mb",
    "nhc_type": "Tropical Storm",
    "nhc_wallet": "AT4",
    "nhc_wind": "50 mph",
    "published": "Wed, 06 Aug 2025 14:43:52 GMT",
    "published_parsed": [
        2025,
        8,
        6,
        14,
        43,
        52,
        2,
        218,
        0
    ],
    "summary": "...DEXTER STRENGTHENS A LITTLE MORE... ...LIKELY TO BECOME A POWERFUL EXTRATROPICAL CYCLONE BY FRIDAY AS IT TRAVERSES THE NORTH ATLANTIC... As of 11:00 AM AST Wed Aug 06 the center of Dexter was located near 39.9, -58.2 with movement ENE at 15 mph. The minimum central pressure was 999 mb with maximum sustained winds of about 50 mph.",
    "summary_detail": {
        "base": "https://www.nhc.noaa.gov/gis-at.xml",
        "language": null,
        "type": "text/html",
        "value": "...DEXTER STRENGTHENS A LITTLE MORE... ...LIKELY TO BECOME A POWERFUL EXTRATROPICAL CYCLONE BY FRIDAY AS IT TRAVERSES THE NORTH ATLANTIC... As of 11:00 AM AST Wed Aug 06 the center of Dexter was located near 39.9, -58.2 with movement ENE at 15 mph. The minimum central pressure was 999 mb with maximum sustained winds of about 50 mph."
    },
    "title": "Summary - Tropical Storm Dexter (AT4/AL042025)",
    "title_detail": {
        "base": "https://www.nhc.noaa.gov/gis-at.xml",
        "language": null,
        "type": "text/plain",
        "value": "Summary - Tropical Storm Dexter (AT4/AL042025)"
    }
}