{
    "author": "nhcwebmaster@noaa.gov (NHC Webmaster)",
    "author_detail": {
        "email": "nhcwebmaster@noaa.gov",
        "name": "NHC Webmaster"
    },
    "authors": [
        {
            "email": "nhcwebmaster@noaa.gov",
            "name": "NHC Webmaster"
        }
    ],
    "guidislink": false,
    "id": "summary-al042024-202408042052",
    "link": "https://www.nhc.noaa.gov/text/refresh/MIATCPAT4+shtml/042051.shtml",
    "links": [
        {
            "href": "https://www.nhc.noaa.gov/text/refresh/MIATCPAT4+shtml/042051.shtml",
            "rel": "alternate",
            "type": "text/html"
        }
    ],
    "nhc_atcf": "AL042024",
    "nhc_center": "27.7, -84.4",
    "nhc_cyclone": "",
    "nhc_datetime": "5:00 PM EDT Sun Aug 4",
    "nhc_headline": "...DEBBY EXPECTED TO BECOME A HURRICANE TONIGHT AND MAKE LANDFALL  IN THE FLORIDA BIG BEND AREA ON MONDAY... ...WILL BRING A MAJOR FLOOD THREAT TO THE SOUTHEASTERN UNITED  STATES...",
    "nhc_movement": "N at 12 mph",
    "nhc_name": "Debby",
    "nhc_pressure": "992 mb",
    "nhc_type": "Tropical Storm",
    "nhc_wallet": "AT4",
    "nhc_wind": "65 mph",
    "published": "Sun, 04 Aug 2024 20:52:03 GMT",
    "published_parsed": [
        2024,
        8,
        4,
        20,
        52,
        3,
        6,
        217,
        0
    ],
    "summary": "...DEBBY EXPECTED TO BECOME A HURRICANE TONIGHT AND MAKE LANDFALL  IN THE FLORIDA BIG BEND AREA ON MONDAY... ...WILL BRING A MAJOR FLOOD THREAT TO THE SOUTHEASTERN UNITED  STATES...\n As of 5:00 PM EDT Sun Aug 4\n the center of Debby was located near 27.7, -84.4\n with movement N at 12 mph.\n The minimum central pressure was 992 mb\n with maximum sustained winds of about 65 mph.",
    "summary_detail": {
        "base": "https://www.nhc.noaa.gov/gis-at.xml",
        "language": null,
        "type": "text/html",
        "value": "...DEBBY EXPECTED TO BECOME A HURRICANE TONIGHT AND MAKE LANDFALL  IN THE FLORIDA BIG BEND AREA ON MONDAY... ...WILL BRING A MAJOR FLOOD THREAT TO THE SOUTHEASTERN UNITED  STATES...\n As of 5:00 PM EDT Sun Aug 4\n the center of Debby was located near 27.7, -84.4\n with movement N at 12 mph.\n The minimum central pressure was 992 mb\n with maximum sustained winds of about 65 mph."
    },
    "title": "Summary - Tropical Storm Debby (AT4/AL042024)",
    "title_detail": {
        "base": "https://www.nhc.noaa.gov/gis-at.xml",
        "language": null,
        "type": "text/plain",
        "value": "Summary - Tropical Storm Debby (AT4/AL042024)"
    }
}