{
    "author": "nhcwebmaster@noaa.gov (NHC Webmaster)",
    "author_detail": {
        "email": "nhcwebmaster@noaa.gov",
        "name": "NHC Webmaster"
    },
    "authors": [
        {
            "email": "nhcwebmaster@noaa.gov",
            "name": "NHC Webmaster"
        }
    ],
    "guidislink": false,
    "id": "summary-al122024-202410020844",
    "link": "https://www.nhc.noaa.gov/text/refresh/MIATCPAT2+shtml/020844.shtml",
    "links": [
        {
            "href": "https://www.nhc.noaa.gov/text/refresh/MIATCPAT2+shtml/020844.shtml",
            "rel": "alternate",
            "type": "text/html"
        }
    ],
    "nhc_atcf": "AL122024",
    "nhc_center": "17.5, -42.1",
    "nhc_cyclone": "",
    "nhc_datetime": "5:00 AM AST Wed Oct 2",
    "nhc_headline": "...KIRK STRENGTHENING AND FORECAST TO GROW LARGER...",
    "nhc_movement": "NW at 14 mph",
    "nhc_name": "Kirk",
    "nhc_pressure": "984 mb",
    "nhc_type": "Hurricane",
    "nhc_wallet": "AT2",
    "nhc_wind": "80 mph",
    "published": "Wed, 02 Oct 2024 08:44:49 GMT",
    "published_parsed": [
        2024,
        10,
        2,
        8,
        44,
        49,
        2,
        276,
        0
    ],
    "summary": "...KIRK STRENGTHENING AND FORECAST TO GROW LARGER...\n As of 5:00 AM AST Wed Oct 2\n the center of Kirk was located near 17.5, -42.1\n with movement NW at 14 mph.\n The minimum central pressure was 984 mb\n with maximum sustained winds of about 80 mph.",
    "summary_detail": {
        "base": "https://www.nhc.noaa.gov/gis-at.xml",
        "language": null,
        "type": "text/html",
        "value": "...KIRK STRENGTHENING AND FORECAST TO GROW LARGER...\n As of 5:00 AM AST Wed Oct 2\n the center of Kirk was located near 17.5, -42.1\n with movement NW at 14 mph.\n The minimum central pressure was 984 mb\n with maximum sustained winds of about 80 mph."
    },
    "title": "Summary - Hurricane Kirk (AT2/AL122024)",
    "title_detail": {
        "base": "https://www.nhc.noaa.gov/gis-at.xml",
        "language": null,
        "type": "text/plain",
        "value": "Summary - Hurricane Kirk (AT2/AL122024)"
    }
}