{
    "author": "nhcwebmaster@noaa.gov (NHC Webmaster)",
    "author_detail": {
        "email": "nhcwebmaster@noaa.gov",
        "name": "NHC Webmaster"
    },
    "authors": [
        {
            "email": "nhcwebmaster@noaa.gov",
            "name": "NHC Webmaster"
        }
    ],
    "guidislink": false,
    "id": "gis-track-kml-cp012024-017-202408261504",
    "link": "https://www.nhc.noaa.gov/storm_graphics/api/CP012024_017adv_TRACK.kmz",
    "links": [
        {
            "href": "https://www.nhc.noaa.gov/storm_graphics/api/CP012024_017adv_TRACK.kmz",
            "rel": "alternate",
            "type": "text/html"
        }
    ],
    "published": "Mon, 26 Aug 2024 15:04:33 GMT",
    "published_parsed": [
        2024,
        8,
        26,
        15,
        4,
        33,
        0,
        239,
        0
    ],
    "summary": "KMZ last updated Mon, 26 Aug 2024 15:04:33 GMT",
    "summary_detail": {
        "base": "https://www.nhc.noaa.gov/gis-cp.xml",
        "language": null,
        "type": "text/html",
        "value": "KMZ last updated Mon, 26 Aug 2024 15:04:33 GMT"
    },
    "title": "Advisory #017 Forecast Track [kmz] - Tropical Storm Hone (CP1/CP012024)",
    "title_detail": {
        "base": "https://www.nhc.noaa.gov/gis-cp.xml",
        "language": null,
        "type": "text/plain",
        "value": "Advisory #017 Forecast Track [kmz] - Tropical Storm Hone (CP1/CP012024)"
    }
}